{
  "gameList": [{
    "name": "Scrabble1",
    "boxArtFile": "scrabble.jpg", 
    "estimatedTime": "1 hour", 
    "numPlayers": "2-4", 
    "rulesComplexity": "easy", 
    "type": "word", 
    "description": "fun word game"
  },{
    "name": "Scrabble2",
    "boxArtFile": "scrabble.jpg", 
    "estimatedTime": "1 hour", 
    "numPlayers": "2-4", 
    "rulesComplexity": "easy", 
    "type": "word", 
    "description": "fun word game fun word game fun word game fun word game fun word game fun word game fun word game fun word gamefun word game fun word game fun word game fun word game"
  },{
    "name": "Scrabble3",
    "boxArtFile": "scrabble.jpg", 
    "estimatedTime": "1 hour", 
    "numPlayers": "2-4", 
    "rulesComplexity": "easy", 
    "type": "word", 
    "description": "fun word game"
  },{
    "name": "Scrabble4",
    "boxArtFile": "scrabble.jpg", 
    "estimatedTime": "1 hour", 
    "numPlayers": "2-4", 
    "rulesComplexity": "easy", 
    "type": "word", 
    "description": "fun word game"
  },{
    "name": "Scrabble5",
    "boxArtFile": "scrabble.jpg", 
    "estimatedTime": "1 hour", 
    "numPlayers": "2-4", 
    "rulesComplexity": "easy", 
    "type": "word", 
    "description": "fun word game"
  },{
    "name": "Scrabble6",
    "boxArtFile": "scrabble.jpg", 
    "estimatedTime": "1 hour", 
    "numPlayers": "2-4", 
    "rulesComplexity": "easy", 
    "type": "word", 
    "description": "fun word game"
  }]
}